mpf/__init__.py
mpf/__main__.py
mpf/_version.py
mpf/config_spec.yaml
mpf/mpfconfig.yaml
mpf/assets/__init__.py
mpf/assets/show.py
mpf/benchmarks/__init__.py
mpf/benchmarks/test_benchmark_events.py
mpf/benchmarks/test_benchmark_light_shows.py
mpf/benchmarks/test_benchmark_switch_hits.py
mpf/benchmarks/machine_files/events/config/config.yaml
mpf/benchmarks/machine_files/shows/config/config.yaml
mpf/benchmarks/machine_files/shows/shows/minimal_light_show.yaml
mpf/benchmarks/machine_files/shows/shows/minimal_light_show_token.yaml
mpf/benchmarks/machine_files/shows/shows/multi_step_tags.yaml
mpf/benchmarks/machine_files/shows/shows/single_step_tag.yaml
mpf/benchmarks/machine_files/switch_hits/config/config.yaml
mpf/commands/__init__.py
mpf/commands/both.py
mpf/commands/build.py
mpf/commands/core.py
mpf/commands/create_config.py
mpf/commands/diagnosis.py
mpf/commands/format.py
mpf/commands/game.py
mpf/commands/hardware.py
mpf/commands/logging_formatters.py
mpf/commands/migrate.py
mpf/commands/scaffold.py
mpf/commands/service.py
mpf/commands/test.py
mpf/commands/wire.py
mpf/config_players/__init__.py
mpf/config_players/bcp_plugin_player.py
mpf/config_players/blinkenlight_player.py
mpf/config_players/block_event_player.py
mpf/config_players/coil_player.py
mpf/config_players/device_config_player.py
mpf/config_players/event_player.py
mpf/config_players/flasher_player.py
mpf/config_players/flat_config_player.py
mpf/config_players/hardware_sound_player.py
mpf/config_players/light_player.py
mpf/config_players/plugin_player.py
mpf/config_players/queue_event_player.py
mpf/config_players/queue_relay_player.py
mpf/config_players/random_event_player.py
mpf/config_players/score_queue_player.py
mpf/config_players/segment_display_player.py
mpf/config_players/show_player.py
mpf/config_players/variable_player.py
mpf/core/__init__.py
mpf/core/assets.py
mpf/core/async_mode.py
mpf/core/ball_controller.py
mpf/core/ball_search.py
mpf/core/case_insensitive_dict.py
mpf/core/clock.py
fast_mpf-0.56.0.dev42.dist-info/AUTHORS
fast_mpf-0.56.0.dev42.dist-info/LICENSE.md
fast_mpf-0.56.0.dev42.dist-info/METADATA
fast_mpf-0.56.0.dev42.dist-info/WHEEL
fast_mpf-0.56.0.dev42.dist-info/entry_points.txt
fast_mpf-0.56.0.dev42.dist-info/top_level.txt
fast_mpf-0.56.0.dev42.dist-info/RECORD
