Metadata-Version: 2.1
Name: fast-mpf
Version: 0.56.0.dev42
Summary: FAST Pinball Mission Pinball Framework
Author-email: Brian Madden <brian@fastpinball.com>
License: MIT
Project-URL: homepage, https://mpf.fastpinball.com
Keywords: pinball
Classifier: Development Status :: 4 - Beta
Classifier: Intended Audience :: Developers
Classifier: License :: OSI Approved :: MIT License
Classifier: Programming Language :: Python :: 3.7
Classifier: Programming Language :: Python :: 3.8
Classifier: Programming Language :: Python :: 3.9
Classifier: Natural Language :: English
Classifier: Operating System :: MacOS :: MacOS X
Classifier: Operating System :: Microsoft :: Windows
Classifier: Operating System :: POSIX :: Linux
Classifier: Topic :: Artistic Software
Classifier: Topic :: Games/Entertainment :: Arcade
Requires-Python: >=3.7
License-File: LICENSE.md
License-File: AUTHORS
Requires-Dist: ruamel.yaml (==0.15.42)
Requires-Dist: pyserial (==3.5)
Requires-Dist: sortedcontainers (==2.3.0)
Requires-Dist: psutil (>=5.7.3)
Requires-Dist: packaging
Requires-Dist: pyserial-asyncio (==0.5) ; platform_system != "Windows"
Requires-Dist: pyserial-asyncio (==0.4) ; platform_system == "Windows"
Provides-Extra: all
Requires-Dist: prompt-toolkit (==3.0.8) ; extra == 'all'
Requires-Dist: asciimatics (==1.12.0) ; extra == 'all'
Requires-Dist: terminaltables (==3.1.0) ; extra == 'all'
Requires-Dist: requests (==2.22.0) ; extra == 'all'
Requires-Dist: irc (==19.0.1) ; extra == 'all'
Requires-Dist: apigpio-mpf (==0.0.3) ; extra == 'all'
Requires-Dist: grpcio-tools (==1.34.0) ; extra == 'all'
Requires-Dist: grpcio (==1.34.0) ; extra == 'all'
Requires-Dist: protobuf (==3.14.0) ; extra == 'all'
Provides-Extra: cli
Requires-Dist: prompt-toolkit (==3.0.8) ; extra == 'cli'
Requires-Dist: asciimatics (==1.12.0) ; extra == 'cli'
Requires-Dist: terminaltables (==3.1.0) ; extra == 'cli'
Provides-Extra: crash_reporter
Requires-Dist: requests (==2.22.0) ; extra == 'crash_reporter'
Provides-Extra: irc
Requires-Dist: irc (==19.0.1) ; extra == 'irc'
Provides-Extra: rpi
Requires-Dist: apigpio-mpf (==0.0.3) ; extra == 'rpi'
Provides-Extra: vpe
Requires-Dist: grpcio-tools (==1.34.0) ; extra == 'vpe'
Requires-Dist: grpcio (==1.34.0) ; extra == 'vpe'
Requires-Dist: protobuf (==3.14.0) ; extra == 'vpe'
